{"Columns":[{"ColumnName":"CurrencyKey","PropertyName":null,"IsPrimaryKey":true},{"ColumnName":"DateKey","PropertyName":null,"IsPrimaryKey":true},{"ColumnName":"AverageRate","PropertyName":null,"IsPrimaryKey":false},{"ColumnName":"EndOfDayRate","PropertyName":null,"IsPrimaryKey":false},{"ColumnName":"Date","PropertyName":null,"IsPrimaryKey":false}],"Actions":[],"Id":"56bae75a-56f1-4f03-9278-23172c508a13","Name":"FactCurrencyRateRoute","Enabled":true,"Prefix":null,"Controller":null,"Resource":"FactCurrencyRate","Schema":"dbo","Table":"FactCurrencyRate","PrimaryKeyColumn":"DateKey","PrimaryKeyColumnDataType":"int"}